{
    "ticker": "CZR",
    "queryCount": 69,
    "resultsCount": 69,
    "adjusted": true,
    "results": [
        {
            "v": 8536013.0,
            "vw": 37.6338,
            "o": 39.75,
            "c": 37.36,
            "h": 39.79,
            "l": 37.08,
            "t": 1722484800000,
            "n": 80454
        },
        {
            "v": 13635368.0,
            "vw": 40.6654,
            "o": 39.81,
            "c": 39.95,
            "h": 41.95,
            "l": 39.5,
            "t": 1722398400000,
            "n": 110782
        },
        {
            "v": 7888405.0,
            "vw": 36.919,
            "o": 36.54,
            "c": 36.9,
            "h": 37.63,
            "l": 36.35,
            "t": 1722312000000,
            "n": 74210
        },
        {
            "v": 5950859.0,
            "vw": 36.083,
            "o": 35.04,
            "c": 36.52,
            "h": 36.58,
            "l": 34.83,
            "t": 1722225600000,
            "n": 51594
        },
        {
            "v": 4586206.0,
            "vw": 34.778,
            "o": 34.355,
            "c": 35.06,
            "h": 35.12,
            "l": 33.78,
            "t": 1721966400000,
            "n": 48353
        },
        {
            "v": 4967740.0,
            "vw": 33.7584,
            "o": 34.28,
            "c": 33.25,
            "h": 34.49,
            "l": 33.21,
            "t": 1721880000000,
            "n": 50897
        },
        {
            "v": 4696048.0,
            "vw": 34.8068,
            "o": 36.34,
            "c": 34.21,
            "h": 36.38,
            "l": 34.14,
            "t": 1721793600000,
            "n": 44598
        },
        {
            "v": 2366190.0,
            "vw": 36.6137,
            "o": 36.14,
            "c": 36.78,
            "h": 36.885,
            "l": 36.07,
            "t": 1721707200000,
            "n": 26131
        },
        {
            "v": 3351851.0,
            "vw": 36.4427,
            "o": 37.13,
            "c": 36.43,
            "h": 37.36,
            "l": 35.93,
            "t": 1721620800000,
            "n": 35608
        },
        {
            "v": 3274464.0,
            "vw": 36.6015,
            "o": 36.66,
            "c": 36.86,
            "h": 36.9,
            "l": 36.06,
            "t": 1721361600000,
            "n": 34431
        },
        {
            "v": 5152294.0,
            "vw": 37.3273,
            "o": 38.4,
            "c": 36.56,
            "h": 39.2,
            "l": 36.39,
            "t": 1721275200000,
            "n": 57118
        },
        {
            "v": 5364072.0,
            "vw": 38.983,
            "o": 38.81,
            "c": 38.5,
            "h": 40.29,
            "l": 38.44,
            "t": 1721188800000,
            "n": 46906
        },
        {
            "v": 5096049.0,
            "vw": 39.2376,
            "o": 39.31,
            "c": 39.77,
            "h": 39.97,
            "l": 38.33,
            "t": 1721102400000,
            "n": 52328
        },
        {
            "v": 5160284.0,
            "vw": 39.5854,
            "o": 39.37,
            "c": 39.22,
            "h": 40.09,
            "l": 39.16,
            "t": 1721016000000,
            "n": 49940
        },
        {
            "v": 5376154.0,
            "vw": 39.9985,
            "o": 39.29,
            "c": 40,
            "h": 40.43,
            "l": 39.01,
            "t": 1720756800000,
            "n": 52687
        },
        {
            "v": 6581264.0,
            "vw": 38.7928,
            "o": 37.49,
            "c": 38.96,
            "h": 39.27,
            "l": 37.275,
            "t": 1720670400000,
            "n": 58644
        },
        {
            "v": 3582457.0,
            "vw": 36.6664,
            "o": 37.18,
            "c": 36.61,
            "h": 37.48,
            "l": 36.27,
            "t": 1720584000000,
            "n": 31739
        },
        {
            "v": 3462518.0,
            "vw": 36.9056,
            "o": 37.46,
            "c": 36.81,
            "h": 37.46,
            "l": 36.41,
            "t": 1720497600000,
            "n": 32977
        },
        {
            "v": 2966675.0,
            "vw": 37.6385,
            "o": 37.39,
            "c": 37.66,
            "h": 37.9,
            "l": 37.2201,
            "t": 1720411200000,
            "n": 30340
        },
        {
            "v": 3249774.0,
            "vw": 37.1869,
            "o": 37.428,
            "c": 37.18,
            "h": 37.99,
            "l": 36.9,
            "t": 1720152000000,
            "n": 29165
        },
        {
            "v": 2458161.0,
            "vw": 37.9884,
            "o": 37.95,
            "c": 37.73,
            "h": 38.945,
            "l": 37.54,
            "t": 1719979200000,
            "n": 21831
        },
        {
            "v": 3367947.0,
            "vw": 37.3095,
            "o": 37.95,
            "c": 37.42,
            "h": 37.97,
            "l": 36.6,
            "t": 1719892800000,
            "n": 35210
        },
        {
            "v": 4822354.0,
            "vw": 38.4271,
            "o": 39.74,
            "c": 37.75,
            "h": 40,
            "l": 37.58,
            "t": 1719806400000,
            "n": 43530
        },
        {
            "v": 5608004.0,
            "vw": 39.674,
            "o": 39.17,
            "c": 39.74,
            "h": 40.23,
            "l": 39.04,
            "t": 1719547200000,
            "n": 37696
        },
        {
            "v": 7279404.0,
            "vw": 38.9331,
            "o": 38.12,
            "c": 39.03,
            "h": 39.7,
            "l": 37.99,
            "t": 1719460800000,
            "n": 39460
        },
        {
            "v": 2487377.0,
            "vw": 38.177,
            "o": 37.53,
            "c": 38.15,
            "h": 38.52,
            "l": 37.53,
            "t": 1719374400000,
            "n": 29368
        },
        {
            "v": 2722821.0,
            "vw": 37.9573,
            "o": 38.89,
            "c": 37.79,
            "h": 38.9,
            "l": 37.555,
            "t": 1719288000000,
            "n": 36666
        },
        {
            "v": 3302547.0,
            "vw": 39.1681,
            "o": 38.93,
            "c": 38.99,
            "h": 39.59,
            "l": 38.59,
            "t": 1719201600000,
            "n": 38523
        },
        {
            "v": 4396900.0,
            "vw": 39.0336,
            "o": 38.75,
            "c": 39.16,
            "h": 39.34,
            "l": 38.46,
            "t": 1718942400000,
            "n": 39020
        },
        {
            "v": 4065828.0,
            "vw": 38.6666,
            "o": 37.26,
            "c": 38.8,
            "h": 39.175,
            "l": 37.19,
            "t": 1718856000000,
            "n": 47464
        },
        {
            "v": 4341054.0,
            "vw": 37.2137,
            "o": 35.9,
            "c": 37.42,
            "h": 37.89,
            "l": 35.9,
            "t": 1718683200000,
            "n": 47624
        },
        {
            "v": 3007727.0,
            "vw": 35.9227,
            "o": 36.02,
            "c": 36.12,
            "h": 36.26,
            "l": 35.31,
            "t": 1718596800000,
            "n": 37259
        },
        {
            "v": 4118946.0,
            "vw": 36.1095,
            "o": 37.38,
            "c": 36.03,
            "h": 37.6,
            "l": 35.52,
            "t": 1718337600000,
            "n": 45163
        },
        {
            "v": 2262107.0,
            "vw": 37.8359,
            "o": 38.1,
            "c": 37.89,
            "h": 38.31,
            "l": 37.56,
            "t": 1718251200000,
            "n": 28065
        },
        {
            "v": 6290275.0,
            "vw": 38.6496,
            "o": 38.63,
            "c": 38.18,
            "h": 39.61,
            "l": 37.92,
            "t": 1718164800000,
            "n": 61494
        },
        {
            "v": 2574900.0,
            "vw": 36.3777,
            "o": 36.25,
            "c": 36.76,
            "h": 36.81,
            "l": 35.38,
            "t": 1718078400000,
            "n": 29978
        },
        {
            "v": 2719907.0,
            "vw": 36.2545,
            "o": 35.87,
            "c": 36.38,
            "h": 36.68,
            "l": 35.55,
            "t": 1717992000000,
            "n": 33171
        },
        {
            "v": 3100632.0,
            "vw": 35.9832,
            "o": 36.1,
            "c": 36.06,
            "h": 36.38,
            "l": 35.56,
            "t": 1717732800000,
            "n": 37236
        },
        {
            "v": 4234184.0,
            "vw": 36.7658,
            "o": 36.31,
            "c": 36.67,
            "h": 37.08,
            "l": 36.08,
            "t": 1717646400000,
            "n": 44783
        },
        {
            "v": 5051310.0,
            "vw": 36.4649,
            "o": 35.54,
            "c": 36.57,
            "h": 36.72,
            "l": 35.5,
            "t": 1717560000000,
            "n": 51541
        },
        {
            "v": 5966307.0,
            "vw": 35.369,
            "o": 35.4,
            "c": 35.51,
            "h": 35.69,
            "l": 34.98,
            "t": 1717473600000,
            "n": 54250
        },
        {
            "v": 5260760.0,
            "vw": 35.3119,
            "o": 35.8,
            "c": 35.62,
            "h": 36.03,
            "l": 34.52,
            "t": 1717387200000,
            "n": 55578
        },
        {
            "v": 26405056.0,
            "vw": 35.6848,
            "o": 32.38,
            "c": 35.56,
            "h": 37.53,
            "l": 32.305,
            "t": 1717128000000,
            "n": 186545
        },
        {
            "v": 4668712.0,
            "vw": 32.1069,
            "o": 32.41,
            "c": 31.85,
            "h": 32.81,
            "l": 31.74,
            "t": 1717041600000,
            "n": 48429
        },
        {
            "v": 4251194.0,
            "vw": 32.1835,
            "o": 32.762,
            "c": 32.15,
            "h": 32.93,
            "l": 31.87,
            "t": 1716955200000,
            "n": 49307
        },
        {
            "v": 3343606.0,
            "vw": 33.392,
            "o": 33.55,
            "c": 33.26,
            "h": 34.15,
            "l": 32.87,
            "t": 1716868800000,
            "n": 37868
        },
        {
            "v": 4873803.0,
            "vw": 33.4911,
            "o": 32.7,
            "c": 33.63,
            "h": 33.9,
            "l": 32.69,
            "t": 1716523200000,
            "n": 46404
        },
        {
            "v": 8181806.0,
            "vw": 33.1718,
            "o": 34.7,
            "c": 32.53,
            "h": 34.85,
            "l": 32.51,
            "t": 1716436800000,
            "n": 69517
        },
        {
            "v": 4842789.0,
            "vw": 34.908,
            "o": 35.28,
            "c": 34.72,
            "h": 35.68,
            "l": 34.385,
            "t": 1716350400000,
            "n": 44726
        },
        {
            "v": 4889369.0,
            "vw": 35.4773,
            "o": 35.85,
            "c": 35.59,
            "h": 36.27,
            "l": 34.96,
            "t": 1716264000000,
            "n": 55750
        },
        {
            "v": 4000133.0,
            "vw": 35.0742,
            "o": 35.46,
            "c": 34.94,
            "h": 35.7,
            "l": 34.58,
            "t": 1716177600000,
            "n": 45701
        },
        {
            "v": 3657935.0,
            "vw": 35.5732,
            "o": 35.31,
            "c": 35.52,
            "h": 35.9,
            "l": 34.92,
            "t": 1715918400000,
            "n": 41160
        },
        {
            "v": 3603288.0,
            "vw": 35.7552,
            "o": 36.32,
            "c": 35.31,
            "h": 36.35,
            "l": 35.29,
            "t": 1715832000000,
            "n": 41001
        },
        {
            "v": 3210645.0,
            "vw": 36.3664,
            "o": 37.31,
            "c": 36.27,
            "h": 37.31,
            "l": 36.09,
            "t": 1715745600000,
            "n": 39060
        },
        {
            "v": 3004167.0,
            "vw": 36.4227,
            "o": 36.59,
            "c": 36.71,
            "h": 36.78,
            "l": 35.9,
            "t": 1715659200000,
            "n": 38370
        },
        {
            "v": 2554190.0,
            "vw": 36.3589,
            "o": 36.39,
            "c": 36.27,
            "h": 37.14,
            "l": 36.06,
            "t": 1715572800000,
            "n": 35499
        },
        {
            "v": 5208337.0,
            "vw": 36.773,
            "o": 37.35,
            "c": 36.18,
            "h": 37.6,
            "l": 36.15,
            "t": 1715313600000,
            "n": 46273
        },
        {
            "v": 3161379.0,
            "vw": 37.0574,
            "o": 36.24,
            "c": 37.3,
            "h": 37.335,
            "l": 35.84,
            "t": 1715227200000,
            "n": 38665
        },
        {
            "v": 2938485.0,
            "vw": 36.179,
            "o": 36.2,
            "c": 36.22,
            "h": 36.48,
            "l": 35.6889,
            "t": 1715140800000,
            "n": 38382
        },
        {
            "v": 3756647.0,
            "vw": 36.4915,
            "o": 36,
            "c": 36.35,
            "h": 36.89,
            "l": 35.945,
            "t": 1715054400000,
            "n": 47057
        },
        {
            "v": 3060197.0,
            "vw": 35.9528,
            "o": 35.88,
            "c": 36.05,
            "h": 36.27,
            "l": 35.49,
            "t": 1714968000000,
            "n": 34621
        },
        {
            "v": 3711516.0,
            "vw": 35.6818,
            "o": 36.09,
            "c": 35.33,
            "h": 36.81,
            "l": 35.11,
            "t": 1714708800000,
            "n": 46605
        },
        {
            "v": 5503788.0,
            "vw": 35.5402,
            "o": 37.4,
            "c": 35.14,
            "h": 37.58,
            "l": 35.09,
            "t": 1714622400000,
            "n": 65315
        },
        {
            "v": 11354257.0,
            "vw": 36.3407,
            "o": 35.32,
            "c": 36.38,
            "h": 37.48,
            "l": 35.12,
            "t": 1714536000000,
            "n": 109916
        },
        {
            "v": 7118242.0,
            "vw": 36.4588,
            "o": 37.22,
            "c": 35.82,
            "h": 37.27,
            "l": 35.76,
            "t": 1714449600000,
            "n": 75076
        },
        {
            "v": 4301165.0,
            "vw": 37.6403,
            "o": 37.24,
            "c": 37.57,
            "h": 38.35,
            "l": 37.07,
            "t": 1714363200000,
            "n": 46399
        },
        {
            "v": 6184741.0,
            "vw": 36.8798,
            "o": 37.45,
            "c": 36.61,
            "h": 38.17,
            "l": 36.34,
            "t": 1714104000000,
            "n": 65928
        },
        {
            "v": 3150143.0,
            "vw": 37.834,
            "o": 37.94,
            "c": 38.04,
            "h": 38.335,
            "l": 37.34,
            "t": 1714017600000,
            "n": 35805
        },
        {
            "v": 3055564.0,
            "vw": 38.4619,
            "o": 39,
            "c": 38.48,
            "h": 39.32,
            "l": 37.98,
            "t": 1713931200000,
            "n": 34154
        }
    ],
    "status": "DELAYED",
    "request_id": "f4fa149ea005c9d35ff2149a373b39ba",
    "count": 69
}